{
  "metadata": {
    "title": "💻 Desarrollo - Guía Técnica COREBOARD",
    "path": "docs/archive/instructivos/desarrollo.md",
    "category": "instructivos",
    "tags": [
      "instructivos",
      "'p', 'br', 'strong', 'em'"
    ],
    "lastUpdated": "2025-11-15",
    "fileName": "desarrollo"
  },
  "content": "# 💻 Desarrollo - Guía Técnica COREBOARD\r\n\r\nDocumentación completa para desarrolladores que trabajan en COREBOARD.\r\n\r\n## 🏗️ Arquitectura Técnica\r\n\r\n### Stack Principal\r\n- **Frontend**: Next.js 14 + TypeScript + Tailwind CSS\r\n- **Backend**: Supabase (PostgreSQL + Auth + Storage)\r\n- **UI**: Radix UI + Lucide Icons\r\n- **State**: React Context + Custom Hooks\r\n- **Forms**: React Hook Form + Zod validation\r\n- **Styling**: Tailwind CSS + CSS Variables\r\n\r\n### Estructura de Carpetas\r\n```\r\ncoreboard/\r\n├── src/\r\n│   ├── components/          # Componentes reutilizables\r\n│   │   ├── ui/             # Componentes base (shadcn/ui)\r\n│   │   ├── views/          # Páginas completas\r\n│   │   └── features/       # Features complejos\r\n│   ├── contexts/           # Context providers (Auth, etc.)\r\n│   ├── stores/             # Estado global (turnosStore)\r\n│   ├── hooks/              # Custom hooks (useTurnos, useAppointments, etc.)\r\n│   ├── lib/                # Utilidades y configuración\r\n│   │   ├── employeeValidator.ts  # Validaciones de empleados\r\n│   │   ├── contextValidator.ts    # Validación de contexto\r\n│   │   └── ...             # Otros validadores\r\n│   ├── types/              # TypeScript definitions\r\n│   └── styles/             # CSS global y themes\r\n├── pages/                  # Next.js pages (App Router)\r\n├── public/                 # Assets estáticos\r\n├── infra/                  # Base de datos y configuración\r\n└── scripts/                # Scripts de automatización\r\n```\r\n\r\n## 🚀 Inicio Rápido\r\n\r\n### Prerrequisitos\r\n```bash\r\nNode.js >= 18.0\r\nnpm >= 8.0\r\nGit\r\n```\r\n\r\n### Instalación\r\n```bash\r\n# Clonar repositorio\r\ngit clone https://github.com/your-org/coreboard.git\r\ncd coreboard\r\n\r\n# Instalar dependencias\r\nnpm install\r\n\r\n# Configurar entorno\r\ncp .env.example .env.local\r\n\r\n# Variables requeridas\r\nNEXT_PUBLIC_SUPABASE_URL=your_supabase_url\r\nNEXT_PUBLIC_SUPABASE_ANON_KEY=your_anon_key\r\nSUPABASE_SERVICE_KEY=your_service_key\r\nNEXT_PUBLIC_DEMO_MODE=false\r\n```\r\n\r\n### Desarrollo Local\r\n```bash\r\n# Iniciar servidor de desarrollo\r\nnpm run dev\r\n\r\n# Construir para producción\r\nnpm run build\r\n\r\n# Ejecutar tests\r\nnpm test\r\n\r\n# Linting\r\nnpm run lint\r\n```\r\n\r\n## 🔧 Scripts de Desarrollo\r\n\r\n### Generar Invitaciones\r\n```bash\r\n# Crear invitación para owner\r\nnode scripts/create_invitation.js owner <org_id> owner@empresa.com\r\n\r\n# Crear invitación para employee\r\nnode scripts/create_invitation.js employee <org_id> empleado@empresa.com\r\n\r\n# Con expiración custom (30 días)\r\nnode scripts/create_invitation.js admin <org_id> admin@empresa.com 30\r\n```\r\n\r\n### Migraciones de Base de Datos\r\n```bash\r\n# Aplicar migraciones (se hace automáticamente al iniciar)\r\n# Las migraciones están en infra/db/schema.sql\r\n\r\n# Verificar estado de BD\r\nnode scripts/db-status.js\r\n```\r\n\r\n### Testing\r\n```bash\r\n# Tests unitarios\r\nnpm run test:unit\r\n\r\n# Tests de integración\r\nnpm run test:integration\r\n\r\n# Tests E2E\r\nnpm run test:e2e\r\n\r\n# Coverage report\r\nnpm run test:coverage\r\n```\r\n\r\n## 📊 Base de Datos\r\n\r\n### Conexión y Configuración\r\n```typescript\r\n// src/lib/supabase.ts\r\nimport { createClient } from '@supabase/supabase-js'\r\n\r\nconst supabaseUrl = process.env.NEXT_PUBLIC_SUPABASE_URL!\r\nconst supabaseKey = process.env.NEXT_PUBLIC_SUPABASE_ANON_KEY!\r\n\r\nexport const supabase = createClient(supabaseUrl, supabaseKey, {\r\n  auth: {\r\n    persistSession: true,\r\n    autoRefreshToken: true\r\n  },\r\n  realtime: {\r\n    params: {\r\n      eventsPerSecond: 10\r\n    }\r\n  }\r\n})\r\n\r\n// Client administrativo (solo server-side)\r\nexport const createAdminSupabaseClient = () => {\r\n  const serviceKey = process.env.SUPABASE_SERVICE_KEY!\r\n  return createClient(supabaseUrl, serviceKey, {\r\n    auth: { autoRefreshToken: false, persistSession: false }\r\n  })\r\n}\r\n```\r\n\r\n### Queries Tipos\r\n```typescript\r\n// Tipos seguros para queries\r\ninterface Turno {\r\n  id: string\r\n  clientName: string\r\n  service: string\r\n  date: string        // YYYY-MM-DD\r\n  time: string        // HH:mm\r\n  status: 'pending' | 'confirmed' | 'completed' | 'cancelled'\r\n  stylist: string\r\n  salonId: string\r\n  notes?: string\r\n  created_by?: string\r\n  total_amount?: number\r\n}\r\n\r\ninterface Employee {\r\n  id: string\r\n  org_id: string\r\n  user_id: string     // OBLIGATORIO - regla de oro\r\n  full_name: string\r\n  email?: string\r\n  phone?: string\r\n  default_commission_pct?: number\r\n  active: boolean\r\n  deleted_at?: string | null\r\n}\r\n\r\ninterface SalonEmployee {\r\n  id: string\r\n  salon_id: string\r\n  employee_id: string\r\n  active: boolean\r\n  assigned_at: string\r\n  assigned_by: string\r\n}\r\n\r\n// Query con RLS automático\r\nconst { data, error } = await supabase\r\n  .from('appointments')\r\n  .select(`\r\n    *,\r\n    salon:salons(name),\r\n    client:clients(name, phone),\r\n    items:appointment_items(\r\n      service:services(name, duration_minutes),\r\n      price,\r\n      quantity\r\n    )\r\n  `)\r\n  .eq('org_id', currentOrgId)\r\n  .gte('date', startDate)\r\n  .lte('date', endDate)\r\n```\r\n\r\n## 🔐 Autenticación y Autorización\r\n\r\n### Context de Auth\r\n```typescript\r\n// src/contexts/AuthContext.tsx\r\ninterface User {\r\n  id: string\r\n  email: string\r\n  memberships: Membership[]\r\n  current_org_id?: string\r\n  isNewUser: boolean\r\n}\r\n\r\ninterface Membership {\r\n  org_id: string\r\n  role: 'owner' | 'admin' | 'employee' | 'viewer'\r\n  is_primary: boolean\r\n}\r\n\r\nconst AuthContext = createContext<{\r\n  user: User | null\r\n  session: Session | null\r\n  loading: boolean\r\n  signIn: (email: string, password: string) => Promise<void>\r\n  signUp: (email: string, password: string, token?: string) => Promise<void>\r\n  signOut: () => Promise<void>\r\n  claimInvitation: (token: string) => Promise<void>\r\n} | null>(null)\r\n```\r\n\r\n### Hooks de Uso Común\r\n\r\n#### useTurnos (Hook Principal) ⭐\r\n```typescript\r\n// src/hooks/useTurnos.ts\r\nexport const useTurnos = (salonId?: string) => {\r\n  const { turnos, loading, filters, setFilters, selectedSalon, setSelectedSalon } = useTurnosStore()\r\n  \r\n  // Selectores\r\n  const turnosByDate = useMemo(() => turnosStore.getByDate(...), [turnos])\r\n  const turnosByStatus = useMemo(() => turnosStore.getByStatus(...), [turnos])\r\n  \r\n  // Acciones\r\n  const createTurno = async (data: Partial<Turno>) => {\r\n    const validation = turnosStore.validateTurno(data)\r\n    if (!validation.valid) throw new Error(validation.message)\r\n    \r\n    const appointment = await createAppointment(data)\r\n    turnosStore.upsert(appointment)\r\n    return appointment\r\n  }\r\n  \r\n  return {\r\n    turnos: filteredTurnos,\r\n    loading,\r\n    filters,\r\n    setFilters,\r\n    createTurno,\r\n    updateTurno,\r\n    deleteTurno,\r\n    validateTurno: turnosStore.validateTurno,\r\n    checkConflicts: turnosStore.checkConflicts\r\n  }\r\n}\r\n```\r\n\r\n#### useAppointments (Legacy - Sincroniza con turnosStore)\r\n```typescript\r\n// src/hooks/useAppointments.ts\r\nexport const useAppointments = (salonId?: string) => {\r\n  const [appointments, setAppointments] = useState<Appointment[]>([])\r\n  const [loading, setLoading] = useState(true)\r\n\r\n  useEffect(() => {\r\n    const fetchAppointments = async () => {\r\n      const { data, error } = await supabase\r\n        .from('appointments')\r\n        .select('*')\r\n        .eq('salon_id', salonId)\r\n        .order('date', { ascending: true })\r\n\r\n      if (error) throw error\r\n      setAppointments(data || [])\r\n      \r\n      // Sincronizar con turnosStore\r\n      const turnos = mapAppointmentsToTurnos(data || [])\r\n      turnosStore.setAll(turnos)\r\n      \r\n      setLoading(false)\r\n    }\r\n\r\n    fetchAppointments()\r\n\r\n    // Suscripción realtime\r\n    const subscription = supabase\r\n      .channel('appointments')\r\n      .on('postgres_changes', {\r\n        event: '*',\r\n        schema: 'public',\r\n        table: 'appointments',\r\n        filter: `salon_id=eq.${salonId}`\r\n      }, (payload) => {\r\n        fetchAppointments()\r\n      })\r\n      .subscribe()\r\n\r\n    return () => subscription.unsubscribe()\r\n  }, [salonId])\r\n\r\n  return { appointments, loading, createAppointment, updateAppointment, deleteAppointment }\r\n}\r\n```\r\n\r\n#### useEmployees y useSalonEmployees\r\n```typescript\r\n// src/hooks/useEmployees.ts\r\nexport const useEmployees = (orgId: string) => {\r\n  // Filtra automáticamente empleados sin user_id (regla de oro)\r\n  const employees = useMemo(() => {\r\n    return filterValidEmployees(rawEmployees)\r\n  }, [rawEmployees])\r\n}\r\n\r\n// src/hooks/useSalonEmployees.ts\r\nexport const useSalonEmployees = (salonId: string) => {\r\n  // Gestiona asignaciones many-to-many entre salones y empleados\r\n  return { salonEmployees, assignEmployee, unassignEmployee }\r\n}\r\n```\r\n\r\n## 🎨 Componentes y UI\r\n\r\n### Patrón de Componentes\r\n```typescript\r\n// Componente base con tipos\r\ninterface ButtonProps extends React.ButtonHTMLAttributes<HTMLButtonElement> {\r\n  variant?: 'primary' | 'secondary' | 'danger'\r\n  size?: 'sm' | 'md' | 'lg'\r\n  loading?: boolean\r\n}\r\n\r\nexport const Button: React.FC<ButtonProps> = ({\r\n  variant = 'primary',\r\n  size = 'md',\r\n  loading = false,\r\n  children,\r\n  className,\r\n  ...props\r\n}) => {\r\n  const baseClasses = \"inline-flex items-center justify-center rounded-md font-medium transition-colors focus:outline-none focus:ring-2 focus:ring-offset-2\"\r\n  const variantClasses = {\r\n    primary: \"bg-blue-600 text-white hover:bg-blue-700 focus:ring-blue-500\",\r\n    secondary: \"bg-gray-200 text-gray-900 hover:bg-gray-300 focus:ring-gray-500\",\r\n    danger: \"bg-red-600 text-white hover:bg-red-700 focus:ring-red-500\"\r\n  }\r\n  const sizeClasses = {\r\n    sm: \"px-3 py-1.5 text-sm\",\r\n    md: \"px-4 py-2 text-base\",\r\n    lg: \"px-6 py-3 text-lg\"\r\n  }\r\n\r\n  return (\r\n    <button\r\n      className={clsx(baseClasses, variantClasses[variant], sizeClasses[size], className)}\r\n      disabled={loading}\r\n      {...props}\r\n    >\r\n      {loading && <Spinner className=\"mr-2\" />}\r\n      {children}\r\n    </button>\r\n  )\r\n}\r\n```\r\n\r\n### Formularios con Validación\r\n```typescript\r\n// src/components/forms/AppointmentForm.tsx\r\nimport { useForm } from 'react-hook-form'\r\nimport { zodResolver } from '@hookform/resolvers/zod'\r\nimport { z } from 'zod'\r\n\r\nconst appointmentSchema = z.object({\r\n  clientName: z.string().min(2, 'Nombre requerido'),\r\n  clientPhone: z.string().regex(/^[\\+]?[1-9][\\d]{0,15}$/, 'Teléfono inválido'),\r\n  date: z.date().min(new Date(), 'Fecha debe ser futura'),\r\n  time: z.string().regex(/^([0-1]?[0-9]|2[0-3]):[0-5][0-9]$/, 'Hora inválida'),\r\n  services: z.array(z.string()).min(1, 'Seleccione al menos un servicio'),\r\n  notes: z.string().optional()\r\n})\r\n\r\ntype AppointmentFormData = z.infer<typeof appointmentSchema>\r\n\r\nexport const AppointmentForm: React.FC = () => {\r\n  const { register, handleSubmit, formState: { errors }, setValue, watch } = useForm<AppointmentFormData>({\r\n    resolver: zodResolver(appointmentSchema)\r\n  })\r\n\r\n  const onSubmit = async (data: AppointmentFormData) => {\r\n    try {\r\n      const { error } = await supabase.from('appointments').insert({\r\n        ...data,\r\n        org_id: currentOrgId,\r\n        status: 'pending'\r\n      })\r\n      if (error) throw error\r\n      toast.success('Turno creado exitosamente')\r\n    } catch (error) {\r\n      toast.error('Error al crear turno')\r\n    }\r\n  }\r\n\r\n  return (\r\n    <form onSubmit={handleSubmit(onSubmit)} className=\"space-y-4\">\r\n      {/* Campos del formulario */}\r\n    </form>\r\n  )\r\n}\r\n```\r\n\r\n## 🧪 Testing\r\n\r\n### Tests Unitarios\r\n```typescript\r\n// src/hooks/__tests__/useAppointments.test.tsx\r\nimport { renderHook, waitFor } from '@testing-library/react'\r\nimport { useAppointments } from '../useAppointments'\r\n\r\nconst mockSupabase = {\r\n  from: jest.fn(() => ({\r\n    select: jest.fn(() => ({\r\n      eq: jest.fn(() => ({\r\n        order: jest.fn(() => Promise.resolve({\r\n          data: mockAppointments,\r\n          error: null\r\n        }))\r\n      }))\r\n    }))\r\n  }))\r\n}\r\n\r\ndescribe('useAppointments', () => {\r\n  beforeEach(() => {\r\n    jest.clearAllMocks()\r\n  })\r\n\r\n  it('should fetch appointments on mount', async () => {\r\n    renderHook(() => useAppointments('org-123'))\r\n\r\n    await waitFor(() => {\r\n      expect(mockSupabase.from).toHaveBeenCalledWith('appointments')\r\n    })\r\n  })\r\n\r\n  it('should return loading state initially', () => {\r\n    const { result } = renderHook(() => useAppointments('org-123'))\r\n    expect(result.current.loading).toBe(true)\r\n  })\r\n})\r\n```\r\n\r\n### Tests de Integración\r\n```typescript\r\n// tests/integration/auth-flow.test.ts\r\ndescribe('Authentication Flow', () => {\r\n  it('should create user and claim invitation', async () => {\r\n    // 1. Crear organización\r\n    const org = await createTestOrg()\r\n\r\n    // 2. Generar token de invitación\r\n    const token = await generateInvitation({\r\n      role: 'employee',\r\n      orgId: org.id,\r\n      email: 'test@example.com'\r\n    })\r\n\r\n    // 3. Registrar usuario\r\n    const user = await signUpWithToken('test@example.com', 'password', token)\r\n\r\n    // 4. Verificar membresía creada\r\n    const membership = await getUserMembership(user.id)\r\n    expect(membership.role).toBe('employee')\r\n    expect(membership.org_id).toBe(org.id)\r\n  })\r\n})\r\n```\r\n\r\n## 🚀 Despliegue\r\n\r\n### Variables de Entorno\r\n```bash\r\n# Producción\r\nNEXT_PUBLIC_SUPABASE_URL=https://xxxxx.supabase.co\r\nNEXT_PUBLIC_SUPABASE_ANON_KEY=eyJhbGciOiJIUzI1NiIs...\r\nSUPABASE_SERVICE_KEY=eyJhbGciOiJIUzI1NiIs...\r\nNEXT_PUBLIC_DEMO_MODE=false\r\n\r\n# Desarrollo\r\nNODE_ENV=development\r\nNEXT_PUBLIC_DEMO_MODE=true\r\n```\r\n\r\n### Build de Producción\r\n```bash\r\n# Build optimizado\r\nnpm run build\r\n\r\n# Verificar bundle size\r\nnpm run analyze\r\n\r\n# Deploy a Vercel/Netlify\r\nnpm run deploy\r\n```\r\n\r\n### CI/CD Pipeline\r\n```yaml\r\n# .github/workflows/deploy.yml\r\nname: Deploy\r\non: [push]\r\njobs:\r\n  test:\r\n    runs-on: ubuntu-latest\r\n    steps:\r\n      - uses: actions/checkout@v3\r\n      - uses: actions/setup-node@v3\r\n        with:\r\n          node-version: '18'\r\n      - run: npm ci\r\n      - run: npm run lint\r\n      - run: npm test\r\n      - run: npm run build\r\n```\r\n\r\n## 🔍 Debugging\r\n\r\n### Logs de Desarrollo\r\n```typescript\r\n// Debug mode\r\nif (process.env.NODE_ENV === 'development') {\r\n  console.log('🔍 Debug:', { user, session, orgId })\r\n}\r\n\r\n// Error boundaries\r\nclass ErrorBoundary extends React.Component {\r\n  componentDidCatch(error: Error, errorInfo: React.ErrorInfo) {\r\n    console.error('❌ Error caught:', error, errorInfo)\r\n    // Reportar a servicio de errores\r\n  }\r\n}\r\n```\r\n\r\n### Queries de Debug\r\n```sql\r\n-- Ver estado de RLS\r\nSELECT schemaname, tablename, policyname, permissive, roles, cmd\r\nFROM pg_policies\r\nWHERE schemaname = 'public'\r\nORDER BY tablename;\r\n\r\n-- Ver conexiones activas\r\nSELECT pid, usename, application_name, client_addr, state\r\nFROM pg_stat_activity\r\nWHERE datname = current_database();\r\n\r\n-- Ver locks activos\r\nSELECT relation::regclass, mode, granted\r\nFROM pg_locks l\r\nJOIN pg_class c ON l.relation = c.oid\r\nWHERE c.relname LIKE 'public.%';\r\n```\r\n\r\n## 📈 Performance\r\n\r\n### Optimizaciones de Queries\r\n```typescript\r\n// Query optimizada con índices\r\nconst { data, error } = await supabase\r\n  .from('appointments')\r\n  .select('id, date, time, status, client_name')\r\n  .eq('org_id', orgId)\r\n  .gte('date', startDate)\r\n  .order('date', { ascending: true })\r\n  .limit(100) // Paginación\r\n```\r\n\r\n### Lazy Loading\r\n```typescript\r\nconst AppointmentsList = lazy(() => import('./AppointmentsList'))\r\n\r\nconst App = () => (\r\n  <Suspense fallback={<AppointmentSkeleton />}>\r\n    <AppointmentsList />\r\n  </Suspense>\r\n)\r\n```\r\n\r\n### Memoización\r\n```typescript\r\nconst filteredAppointments = useMemo(() => {\r\n  return appointments.filter(apt =>\r\n    apt.status === filterStatus &&\r\n    apt.date >= dateRange.start &&\r\n    apt.date <= dateRange.end\r\n  )\r\n}, [appointments, filterStatus, dateRange])\r\n```\r\n\r\n## 🔒 Seguridad\r\n\r\n### Validación de Input\r\n```typescript\r\nimport { z } from 'zod'\r\n\r\nconst userSchema = z.object({\r\n  email: z.string().email().max(255),\r\n  password: z.string().min(8).max(128),\r\n  role: z.enum(['owner', 'admin', 'employee', 'viewer'])\r\n})\r\n\r\nconst validateUser = (data: unknown) => {\r\n  return userSchema.parse(data)\r\n}\r\n```\r\n\r\n### Sanitización\r\n```typescript\r\nimport DOMPurify from 'dompurify'\r\n\r\nconst sanitizeHtml = (html: string) => {\r\n  return DOMPurify.sanitize(html, {\r\n    ALLOWED_TAGS: ['p', 'br', 'strong', 'em'],\r\n    ALLOWED_ATTR: []\r\n  })\r\n}\r\n```\r\n\r\n## 📚 Recursos Adicionales\r\n\r\n### Documentación Oficial\r\n- [Next.js Docs](https://nextjs.org/docs)\r\n- [Supabase Docs](https://supabase.com/docs)\r\n- [Tailwind CSS](https://tailwindcss.com/docs)\r\n- [TypeScript Handbook](https://www.typescriptlang.org/docs/)\r\n\r\n### Herramientas de Desarrollo\r\n- [React DevTools](https://react.dev/learn/react-developer-tools)\r\n- [Supabase Studio](https://supabase.com/dashboard)\r\n- [Vercel Analytics](https://vercel.com/analytics)\r\n\r\n### Comunidad\r\n- [Discord de Supabase](https://supabase.com/discord)\r\n- [Next.js Community](https://nextjs.org/community)\r\n- [Reactiflux](https://www.reactiflux.com/)\r\n\r\n---\r\n\r\n**Versión:** 2.0.0\r\n**Última actualización:** Noviembre 2025\r\n\r\n## 📋 Cambios Recientes (v2.0.0)\r\n\r\n### Sistema Global de Turnos\r\n- ✅ **`src/stores/turnosStore.ts`**: Estado centralizado para turnos\r\n- ✅ **`src/hooks/useTurnos.ts`**: Hook de alto nivel (recomendado usar este)\r\n- ✅ **`useAppointments`**: Mantenido para compatibilidad, sincroniza con turnosStore\r\n\r\n### Gestión de Empleados\r\n- ✅ **`src/lib/employeeValidator.ts`**: Validaciones centralizadas\r\n- ✅ **Tabla `salon_employees`**: Asignaciones many-to-many\r\n- ✅ **Regla de oro**: user_id obligatorio en `app.employees`\r\n",
  "sections": []
}